topsis_ashpreet_102303263/__init__.py
topsis_ashpreet_102303263/topsis.py
topsis_ashpreet_102303263-1.0.2.dist-info/METADATA
topsis_ashpreet_102303263-1.0.2.dist-info/WHEEL
topsis_ashpreet_102303263-1.0.2.dist-info/entry_points.txt
topsis_ashpreet_102303263-1.0.2.dist-info/top_level.txt
topsis_ashpreet_102303263-1.0.2.dist-info/RECORD
