Metadata-Version: 2.4
Name: Topsis-Ashpreet-102303263
Version: 1.0.2
Requires-Dist: pandas
Requires-Dist: numpy
Dynamic: description
Dynamic: description-content-type
Dynamic: requires-dist
